consul_async_register/__init__.py
consul_async_register/register.py
consul_async_register-0.0.1.dist-info/METADATA
consul_async_register-0.0.1.dist-info/WHEEL
consul_async_register-0.0.1.dist-info/top_level.txt
consul_async_register-0.0.1.dist-info/RECORD
