Metadata-Version: 2.4
Name: consul-async-register
Version: 0.0.1
Summary: Lightweight asynchronous microservices Registration module in HashiCorp Consul
Author: TheAtrii
Requires-Dist: aiohttp>=3.8.9
Dynamic: author
Dynamic: requires-dist
Dynamic: summary
